aioxcom/__init__.py
aioxcom/xcom_api_base.py
aioxcom/xcom_api_serial.py
aioxcom/xcom_api_tcp.py
aioxcom/xcom_api_udp.py
aioxcom/xcom_const.py
aioxcom/xcom_data.py
aioxcom/xcom_datapoints.py
aioxcom/xcom_datapoints_120v.json
aioxcom/xcom_datapoints_240v.json
aioxcom/xcom_discover.py
aioxcom/xcom_families.py
aioxcom/xcom_messages.py
aioxcom/xcom_messages_en.json
aioxcom/xcom_protocol.py
aioxcom/xcom_values.py
aioxcom-2.5.0.dist-info/licenses/LICENSE
aioxcom-2.5.0.dist-info/METADATA
aioxcom-2.5.0.dist-info/WHEEL
aioxcom-2.5.0.dist-info/top_level.txt
aioxcom-2.5.0.dist-info/RECORD
