Metadata-Version: 2.4
Name: aioxcom
Version: 2.5.0
Summary: Depricated. Please use pystuderxcom library instead.
Author-email: Anko Hanse <anko_hanse@hotmail.com>
Project-URL: Homepage, https://github.com/ankohanse/aioxcom
Project-URL: Issues, https://github.com/ankohanse/aioxcom/issues
Classifier: Programming Language :: Python :: 3
Classifier: License :: OSI Approved :: GNU General Public License v3 or later (GPLv3+)
Classifier: Operating System :: OS Independent
Requires-Python: >=3.8
License-File: LICENSE
Requires-Dist: getmac<1.0.0
Requires-Dist: pyserial-asyncio<1.0
Requires-Dist: asyncudp<1.0.0
Provides-Extra: tests
Requires-Dist: pytest; extra == "tests"
Requires-Dist: pytest-asyncio; extra == "tests"
Dynamic: license-file
